{"week":{"id":"0009","link":"https://virtual.ifro.edu.br/jiparana/mod/forum/discuss.php?d=19637","title":"HORÁRIO SEMANAL DO TÉCNICO - 19 A 24/09/2022","pdfURL":"https://virtual.ifro.edu.br/jiparana/pluginfile.php/50/mod_forum/post/48393/Hor%C3%A1rio%2019%20a%2024%20de%20setembro.pdf","publishedAt":"2022-09-16T23:58:33.000Z","startsAt":"2022-09-19T04:00:00.000Z","endsAt":"2022-09-25T03:59:00.000Z"},"teacher":{"id":"tcher_c8t","fullName":null,"slugs":[{"id":34,"slug":"Elise"}]},"items":[{"id":7446,"order":5,"klass":{"id":"quimica-2-B","year":"2","course":"quimica","label":"B","slugs":[{"id":10,"slug":"2ºB QUI"}]},"subject":{"id":"subj_fg7","name":null,"slugs":[{"id":35,"slug":"Q. Anali."}]},"weekDayOrder":1,"absoluteDay":1663646400000},{"id":7447,"order":6,"klass":{"id":"quimica-2-B","year":"2","course":"quimica","label":"B","slugs":[{"id":10,"slug":"2ºB QUI"}]},"subject":{"id":"subj_fg7","name":null,"slugs":[{"id":35,"slug":"Q. Anali."}]},"weekDayOrder":1,"absoluteDay":1663646400000},{"id":7439,"order":8,"klass":{"id":"quimica-2-A","year":"2","course":"quimica","label":"A","slugs":[{"id":9,"slug":"2ºA QUI"}]},"subject":{"id":"subj_fg7","name":null,"slugs":[{"id":35,"slug":"Q. Anali."}]},"weekDayOrder":1,"absoluteDay":1663646400000},{"id":7440,"order":9,"klass":{"id":"quimica-2-A","year":"2","course":"quimica","label":"A","slugs":[{"id":9,"slug":"2ºA QUI"}]},"subject":{"id":"subj_fg7","name":null,"slugs":[{"id":35,"slug":"Q. Anali."}]},"weekDayOrder":1,"absoluteDay":1663646400000},{"id":7571,"order":0,"klass":{"id":"quimica-1-B","year":"1","course":"quimica","label":"B","slugs":[{"id":8,"slug":"1ºB QUI"}]},"subject":{"id":"subj_tv5","name":null,"slugs":[{"id":30,"slug":"Q. Amb."}]},"weekDayOrder":2,"absoluteDay":1663732800000},{"id":7572,"order":1,"klass":{"id":"quimica-1-B","year":"1","course":"quimica","label":"B","slugs":[{"id":8,"slug":"1ºB QUI"}]},"subject":{"id":"subj_tv5","name":null,"slugs":[{"id":30,"slug":"Q. Amb."}]},"weekDayOrder":2,"absoluteDay":1663732800000},{"id":7563,"order":2,"klass":{"id":"quimica-1-A","year":"1","course":"quimica","label":"A","slugs":[{"id":7,"slug":"1ºA QUI"}]},"subject":{"id":"subj_tv5","name":null,"slugs":[{"id":30,"slug":"Q. Amb."}]},"weekDayOrder":2,"absoluteDay":1663732800000},{"id":7564,"order":3,"klass":{"id":"quimica-1-A","year":"1","course":"quimica","label":"A","slugs":[{"id":7,"slug":"1ºA QUI"}]},"subject":{"id":"subj_tv5","name":null,"slugs":[{"id":30,"slug":"Q. Amb."}]},"weekDayOrder":2,"absoluteDay":1663732800000}]}