{"week":{"id":"0005","link":"https://virtual.ifro.edu.br/jiparana/mod/forum/discuss.php?d=19542","title":"HORÁRIO SEMANAL DO TÉCNICO - 22 a 27/08/2022","pdfURL":"https://virtual.ifro.edu.br/jiparana/pluginfile.php/50/mod_forum/post/48223/Hor%C3%A1rio%2022%20a%2027%20de%20agosto.pdf","publishedAt":"2022-08-21T14:05:10.000Z","startsAt":"2022-08-22T04:00:00.000Z","endsAt":"2022-08-28T03:59:00.000Z"},"teacher":{"id":"tcher_5mW","fullName":null,"slugs":[{"id":27,"slug":"Fabrício"}]},"items":[{"id":4102,"order":1,"klass":{"id":"informatica-3-B","year":"3","course":"informatica","label":"B","slugs":[{"id":6,"slug":"3ºB INF"}]},"subject":{"id":"subj_28r","name":null,"slugs":[{"id":1,"slug":"Ed. Física"}]},"weekDayOrder":3,"absoluteDay":1661400000000},{"id":4103,"order":2,"klass":{"id":"informatica-3-B","year":"3","course":"informatica","label":"B","slugs":[{"id":6,"slug":"3ºB INF"}]},"subject":{"id":"subj_28r","name":null,"slugs":[{"id":1,"slug":"Ed. Física"}]},"weekDayOrder":3,"absoluteDay":1661400000000},{"id":4311,"order":0,"klass":{"id":"quimica-3-B","year":"3","course":"quimica","label":"B","slugs":[{"id":12,"slug":"3ºB QUI"}]},"subject":{"id":"subj_28r","name":null,"slugs":[{"id":1,"slug":"Ed. Física"}]},"weekDayOrder":4,"absoluteDay":1661486400000},{"id":4312,"order":1,"klass":{"id":"quimica-3-B","year":"3","course":"quimica","label":"B","slugs":[{"id":12,"slug":"3ºB QUI"}]},"subject":{"id":"subj_28r","name":null,"slugs":[{"id":1,"slug":"Ed. Física"}]},"weekDayOrder":4,"absoluteDay":1661486400000},{"id":4344,"order":3,"klass":{"id":"florestas-3-A","year":"3","course":"florestas","label":"A","slugs":[{"id":15,"slug":"3ºA FLOR"}]},"subject":{"id":"subj_28r","name":null,"slugs":[{"id":1,"slug":"Ed. Física"}]},"weekDayOrder":4,"absoluteDay":1661486400000},{"id":4345,"order":4,"klass":{"id":"florestas-3-A","year":"3","course":"florestas","label":"A","slugs":[{"id":15,"slug":"3ºA FLOR"}]},"subject":{"id":"subj_28r","name":null,"slugs":[{"id":1,"slug":"Ed. Física"}]},"weekDayOrder":4,"absoluteDay":1661486400000},{"id":4307,"order":6,"klass":{"id":"quimica-3-A","year":"3","course":"quimica","label":"A","slugs":[{"id":11,"slug":"3ºA QUI"}]},"subject":{"id":"subj_28r","name":null,"slugs":[{"id":1,"slug":"Ed. Física"}]},"weekDayOrder":4,"absoluteDay":1661486400000},{"id":4308,"order":7,"klass":{"id":"quimica-3-A","year":"3","course":"quimica","label":"A","slugs":[{"id":11,"slug":"3ºA QUI"}]},"subject":{"id":"subj_28r","name":null,"slugs":[{"id":1,"slug":"Ed. Física"}]},"weekDayOrder":4,"absoluteDay":1661486400000},{"id":4249,"order":8,"klass":{"id":"informatica-3-A","year":"3","course":"informatica","label":"A","slugs":[{"id":5,"slug":"3ºA INF"}]},"subject":{"id":"subj_28r","name":null,"slugs":[{"id":1,"slug":"Ed. Física"}]},"weekDayOrder":4,"absoluteDay":1661486400000},{"id":4250,"order":9,"klass":{"id":"informatica-3-A","year":"3","course":"informatica","label":"A","slugs":[{"id":5,"slug":"3ºA INF"}]},"subject":{"id":"subj_28r","name":null,"slugs":[{"id":1,"slug":"Ed. Física"}]},"weekDayOrder":4,"absoluteDay":1661486400000},{"id":4461,"order":0,"klass":{"id":"quimica-3-B","year":"3","course":"quimica","label":"B","slugs":[{"id":12,"slug":"3ºB QUI"}]},"subject":{"id":"subj_28r","name":null,"slugs":[{"id":1,"slug":"Ed. Física"}]},"weekDayOrder":5,"absoluteDay":1661572800000},{"id":4462,"order":1,"klass":{"id":"quimica-3-B","year":"3","course":"quimica","label":"B","slugs":[{"id":12,"slug":"3ºB QUI"}]},"subject":{"id":"subj_28r","name":null,"slugs":[{"id":1,"slug":"Ed. Física"}]},"weekDayOrder":5,"absoluteDay":1661572800000},{"id":4494,"order":3,"klass":{"id":"florestas-3-A","year":"3","course":"florestas","label":"A","slugs":[{"id":15,"slug":"3ºA FLOR"}]},"subject":{"id":"subj_28r","name":null,"slugs":[{"id":1,"slug":"Ed. Física"}]},"weekDayOrder":5,"absoluteDay":1661572800000},{"id":4495,"order":4,"klass":{"id":"florestas-3-A","year":"3","course":"florestas","label":"A","slugs":[{"id":15,"slug":"3ºA FLOR"}]},"subject":{"id":"subj_28r","name":null,"slugs":[{"id":1,"slug":"Ed. Física"}]},"weekDayOrder":5,"absoluteDay":1661572800000},{"id":4457,"order":6,"klass":{"id":"quimica-3-A","year":"3","course":"quimica","label":"A","slugs":[{"id":11,"slug":"3ºA QUI"}]},"subject":{"id":"subj_28r","name":null,"slugs":[{"id":1,"slug":"Ed. Física"}]},"weekDayOrder":5,"absoluteDay":1661572800000},{"id":4458,"order":7,"klass":{"id":"quimica-3-A","year":"3","course":"quimica","label":"A","slugs":[{"id":11,"slug":"3ºA QUI"}]},"subject":{"id":"subj_28r","name":null,"slugs":[{"id":1,"slug":"Ed. Física"}]},"weekDayOrder":5,"absoluteDay":1661572800000},{"id":4399,"order":8,"klass":{"id":"informatica-3-A","year":"3","course":"informatica","label":"A","slugs":[{"id":5,"slug":"3ºA INF"}]},"subject":{"id":"subj_28r","name":null,"slugs":[{"id":1,"slug":"Ed. Física"}]},"weekDayOrder":5,"absoluteDay":1661572800000},{"id":4400,"order":9,"klass":{"id":"informatica-3-A","year":"3","course":"informatica","label":"A","slugs":[{"id":5,"slug":"3ºA INF"}]},"subject":{"id":"subj_28r","name":null,"slugs":[{"id":1,"slug":"Ed. Física"}]},"weekDayOrder":5,"absoluteDay":1661572800000}]}