{"week":{"id":"000f","link":"https://virtual.ifro.edu.br/jiparana/mod/forum/discuss.php?d=19711","title":"HORÁRIO SEMANAL DO TÉCNICO - 31/10 A 05/11/2022","pdfURL":"https://virtual.ifro.edu.br/jiparana/pluginfile.php/50/mod_forum/post/48557/Hor%C3%A1rio%2031%20de%20outubro%20a%2005%20de%20novembro.pdf","publishedAt":"2022-10-26T20:57:26.000Z","startsAt":"2022-10-31T04:00:00.000Z","endsAt":"2022-11-06T03:59:00.000Z"},"teacher":{"id":"tcher_1J2","fullName":null,"slugs":[{"id":51,"slug":"Lorena"}]},"items":[{"id":12873,"order":2,"klass":{"id":"florestas-1-A","year":"1","course":"florestas","label":"A","slugs":[{"id":13,"slug":"1ºA FLOR"}]},"subject":{"id":"subj_2HL","name":null,"slugs":[{"id":48,"slug":"Prot.Flor."}]},"weekDayOrder":1,"absoluteDay":1667275200000},{"id":12874,"order":3,"klass":{"id":"florestas-1-A","year":"1","course":"florestas","label":"A","slugs":[{"id":13,"slug":"1ºA FLOR"}]},"subject":{"id":"subj_2HL","name":null,"slugs":[{"id":48,"slug":"Prot.Flor."}]},"weekDayOrder":1,"absoluteDay":1667275200000},{"id":13041,"order":0,"klass":{"id":"florestas-3-A","year":"3","course":"florestas","label":"A","slugs":[{"id":15,"slug":"3ºA FLOR"}]},"subject":{"id":"subj_gJs","name":null,"slugs":[{"id":56,"slug":"I. M. Flor."}]},"weekDayOrder":2,"absoluteDay":1667361600000},{"id":13042,"order":1,"klass":{"id":"florestas-3-A","year":"3","course":"florestas","label":"A","slugs":[{"id":15,"slug":"3ºA FLOR"}]},"subject":{"id":"subj_gJs","name":null,"slugs":[{"id":56,"slug":"I. M. Flor."}]},"weekDayOrder":2,"absoluteDay":1667361600000},{"id":13043,"order":2,"klass":{"id":"florestas-3-A","year":"3","course":"florestas","label":"A","slugs":[{"id":15,"slug":"3ºA FLOR"}]},"subject":{"id":"subj_gJs","name":null,"slugs":[{"id":56,"slug":"I. M. Flor."}]},"weekDayOrder":2,"absoluteDay":1667361600000},{"id":13491,"order":0,"klass":{"id":"florestas-3-A","year":"3","course":"florestas","label":"A","slugs":[{"id":15,"slug":"3ºA FLOR"}]},"subject":{"id":"subj_gJs","name":null,"slugs":[{"id":56,"slug":"I. M. Flor."}]},"weekDayOrder":5,"absoluteDay":1667620800000},{"id":13492,"order":1,"klass":{"id":"florestas-3-A","year":"3","course":"florestas","label":"A","slugs":[{"id":15,"slug":"3ºA FLOR"}]},"subject":{"id":"subj_gJs","name":null,"slugs":[{"id":56,"slug":"I. M. Flor."}]},"weekDayOrder":5,"absoluteDay":1667620800000},{"id":13493,"order":2,"klass":{"id":"florestas-3-A","year":"3","course":"florestas","label":"A","slugs":[{"id":15,"slug":"3ºA FLOR"}]},"subject":{"id":"subj_gJs","name":null,"slugs":[{"id":56,"slug":"I. M. Flor."}]},"weekDayOrder":5,"absoluteDay":1667620800000}]}