{"week":{"id":"000a","link":"https://virtual.ifro.edu.br/jiparana/mod/forum/discuss.php?d=19656","title":"HORÁRIO SEMANAL DO TÉCNICO - 26/09 A 01/10/2022","pdfURL":"https://virtual.ifro.edu.br/jiparana/pluginfile.php/50/mod_forum/post/48437/Hor%C3%A1rio%2026%20de%20setembro%20a%2001%20de%20outubro.pdf","publishedAt":"2022-09-25T01:38:35.000Z","startsAt":"2022-09-26T04:00:00.000Z","endsAt":"2022-10-02T03:59:00.000Z"},"teacher":{"id":"tcher_5mW","fullName":null,"slugs":[{"id":27,"slug":"Fabrício"}]},"items":[{"id":8504,"order":3,"klass":{"id":"quimica-3-A","year":"3","course":"quimica","label":"A","slugs":[{"id":11,"slug":"3ºA QUI"}]},"subject":{"id":"subj_28r","name":null,"slugs":[{"id":1,"slug":"Ed. Física"}]},"weekDayOrder":2,"absoluteDay":1664337600000},{"id":8505,"order":4,"klass":{"id":"quimica-3-A","year":"3","course":"quimica","label":"A","slugs":[{"id":11,"slug":"3ºA QUI"}]},"subject":{"id":"subj_28r","name":null,"slugs":[{"id":1,"slug":"Ed. Física"}]},"weekDayOrder":2,"absoluteDay":1664337600000},{"id":8602,"order":1,"klass":{"id":"informatica-3-B","year":"3","course":"informatica","label":"B","slugs":[{"id":6,"slug":"3ºB INF"}]},"subject":{"id":"subj_28r","name":null,"slugs":[{"id":1,"slug":"Ed. Física"}]},"weekDayOrder":3,"absoluteDay":1664424000000},{"id":8603,"order":2,"klass":{"id":"informatica-3-B","year":"3","course":"informatica","label":"B","slugs":[{"id":6,"slug":"3ºB INF"}]},"subject":{"id":"subj_28r","name":null,"slugs":[{"id":1,"slug":"Ed. Física"}]},"weekDayOrder":3,"absoluteDay":1664424000000},{"id":8594,"order":3,"klass":{"id":"informatica-3-A","year":"3","course":"informatica","label":"A","slugs":[{"id":5,"slug":"3ºA INF"}]},"subject":{"id":"subj_28r","name":null,"slugs":[{"id":1,"slug":"Ed. Física"}]},"weekDayOrder":3,"absoluteDay":1664424000000},{"id":8595,"order":4,"klass":{"id":"informatica-3-A","year":"3","course":"informatica","label":"A","slugs":[{"id":5,"slug":"3ºA INF"}]},"subject":{"id":"subj_28r","name":null,"slugs":[{"id":1,"slug":"Ed. Física"}]},"weekDayOrder":3,"absoluteDay":1664424000000},{"id":8811,"order":0,"klass":{"id":"quimica-3-B","year":"3","course":"quimica","label":"B","slugs":[{"id":12,"slug":"3ºB QUI"}]},"subject":{"id":"subj_28r","name":null,"slugs":[{"id":1,"slug":"Ed. Física"}]},"weekDayOrder":4,"absoluteDay":1664510400000},{"id":8812,"order":1,"klass":{"id":"quimica-3-B","year":"3","course":"quimica","label":"B","slugs":[{"id":12,"slug":"3ºB QUI"}]},"subject":{"id":"subj_28r","name":null,"slugs":[{"id":1,"slug":"Ed. Física"}]},"weekDayOrder":4,"absoluteDay":1664510400000},{"id":8844,"order":3,"klass":{"id":"florestas-3-A","year":"3","course":"florestas","label":"A","slugs":[{"id":15,"slug":"3ºA FLOR"}]},"subject":{"id":"subj_28r","name":null,"slugs":[{"id":1,"slug":"Ed. Física"}]},"weekDayOrder":4,"absoluteDay":1664510400000},{"id":8845,"order":4,"klass":{"id":"florestas-3-A","year":"3","course":"florestas","label":"A","slugs":[{"id":15,"slug":"3ºA FLOR"}]},"subject":{"id":"subj_28r","name":null,"slugs":[{"id":1,"slug":"Ed. Física"}]},"weekDayOrder":4,"absoluteDay":1664510400000},{"id":8954,"order":3,"klass":{"id":"quimica-3-A","year":"3","course":"quimica","label":"A","slugs":[{"id":11,"slug":"3ºA QUI"}]},"subject":{"id":"subj_28r","name":null,"slugs":[{"id":1,"slug":"Ed. Física"}]},"weekDayOrder":5,"absoluteDay":1664596800000},{"id":8955,"order":4,"klass":{"id":"quimica-3-A","year":"3","course":"quimica","label":"A","slugs":[{"id":11,"slug":"3ºA QUI"}]},"subject":{"id":"subj_28r","name":null,"slugs":[{"id":1,"slug":"Ed. Física"}]},"weekDayOrder":5,"absoluteDay":1664596800000}]}