{"week":{"id":"0004","link":"https://virtual.ifro.edu.br/jiparana/mod/forum/discuss.php?d=19518","title":"HORÁRIO SEMANAL DO TÉCNICO - 15 a 20/08/2022","pdfURL":"https://virtual.ifro.edu.br/jiparana/pluginfile.php/50/mod_forum/post/48144/Hor%C3%A1rio%2015%20a%2020%20de%20agosto.pdf","publishedAt":"2022-08-12T20:26:44.000Z","startsAt":"2022-08-15T04:00:00.000Z","endsAt":"2022-08-21T03:59:00.000Z"},"klass":{"id":"informatica-2-B","year":"2","course":"informatica","label":"B","slugs":[{"id":4,"slug":"2ºB INF"}]},"items":[{"id":2731,"order":0,"subject":null,"teacher":null,"weekDayOrder":0,"absoluteDay":1660536000000},{"id":2732,"order":1,"subject":null,"teacher":null,"weekDayOrder":0,"absoluteDay":1660536000000},{"id":2733,"order":2,"subject":null,"teacher":null,"weekDayOrder":0,"absoluteDay":1660536000000},{"id":2734,"order":3,"subject":null,"teacher":null,"weekDayOrder":0,"absoluteDay":1660536000000},{"id":2735,"order":4,"subject":null,"teacher":null,"weekDayOrder":0,"absoluteDay":1660536000000},{"id":2736,"order":5,"subject":{"id":"subj_saK","name":null,"slugs":[{"id":20,"slug":"F.A. Sistemas"}]},"teacher":{"id":"tcher_2CE","fullName":null,"slugs":[{"id":13,"slug":"Tiago"}]},"weekDayOrder":0,"absoluteDay":1660536000000},{"id":2737,"order":6,"subject":{"id":"subj_saK","name":null,"slugs":[{"id":20,"slug":"F.A. Sistemas"}]},"teacher":{"id":"tcher_2CE","fullName":null,"slugs":[{"id":13,"slug":"Tiago"}]},"weekDayOrder":0,"absoluteDay":1660536000000},{"id":2738,"order":7,"subject":{"id":"subj_k5f","name":null,"slugs":[{"id":64,"slug":"CPA"}]},"teacher":{"id":"tcher_2CE","fullName":null,"slugs":[{"id":13,"slug":"Tiago"}]},"weekDayOrder":0,"absoluteDay":1660536000000},{"id":2739,"order":8,"subject":{"id":"subj_wG8","name":null,"slugs":[{"id":15,"slug":"P .O.O."}]},"teacher":{"id":"tcher_7c6","fullName":null,"slugs":[{"id":17,"slug":"Reinaldo"}]},"weekDayOrder":0,"absoluteDay":1660536000000},{"id":2740,"order":9,"subject":{"id":"subj_wG8","name":null,"slugs":[{"id":15,"slug":"P .O.O."}]},"teacher":{"id":"tcher_7c6","fullName":null,"slugs":[{"id":17,"slug":"Reinaldo"}]},"weekDayOrder":0,"absoluteDay":1660536000000},{"id":2881,"order":0,"subject":{"id":"subj_qSL","name":null,"slugs":[{"id":4,"slug":"Matemática"}]},"teacher":{"id":"tcher_6dJ","fullName":null,"slugs":[{"id":15,"slug":"Mauro"}]},"weekDayOrder":1,"absoluteDay":1660622400000},{"id":2882,"order":1,"subject":{"id":"subj_qSL","name":null,"slugs":[{"id":4,"slug":"Matemática"}]},"teacher":{"id":"tcher_6dJ","fullName":null,"slugs":[{"id":15,"slug":"Mauro"}]},"weekDayOrder":1,"absoluteDay":1660622400000},{"id":2883,"order":2,"subject":{"id":"subj_28r","name":null,"slugs":[{"id":1,"slug":"Ed. Física"}]},"teacher":{"id":"tcher_f8D","fullName":null,"slugs":[{"id":19,"slug":"Edivan"}]},"weekDayOrder":1,"absoluteDay":1660622400000},{"id":2884,"order":3,"subject":{"id":"subj_28r","name":null,"slugs":[{"id":1,"slug":"Ed. Física"}]},"teacher":{"id":"tcher_f8D","fullName":null,"slugs":[{"id":19,"slug":"Edivan"}]},"weekDayOrder":1,"absoluteDay":1660622400000},{"id":2885,"order":4,"subject":null,"teacher":null,"weekDayOrder":1,"absoluteDay":1660622400000},{"id":2886,"order":5,"subject":{"id":"subj_qqD","name":null,"slugs":[{"id":10,"slug":"Geografia"}]},"teacher":{"id":"tcher_19L","fullName":null,"slugs":[{"id":9,"slug":"Jania"}]},"weekDayOrder":1,"absoluteDay":1660622400000},{"id":2887,"order":6,"subject":{"id":"subj_qqD","name":null,"slugs":[{"id":10,"slug":"Geografia"}]},"teacher":{"id":"tcher_19L","fullName":null,"slugs":[{"id":9,"slug":"Jania"}]},"weekDayOrder":1,"absoluteDay":1660622400000},{"id":2888,"order":7,"subject":{"id":"subj_aMB","name":null,"slugs":[{"id":19,"slug":"L. Progr."}]},"teacher":{"id":"tcher_7c6","fullName":null,"slugs":[{"id":17,"slug":"Reinaldo"}]},"weekDayOrder":1,"absoluteDay":1660622400000},{"id":2889,"order":8,"subject":{"id":"subj_aMB","name":null,"slugs":[{"id":19,"slug":"L. Progr."}]},"teacher":{"id":"tcher_7c6","fullName":null,"slugs":[{"id":17,"slug":"Reinaldo"}]},"weekDayOrder":1,"absoluteDay":1660622400000},{"id":2890,"order":9,"subject":null,"teacher":null,"weekDayOrder":1,"absoluteDay":1660622400000},{"id":3031,"order":0,"subject":{"id":"subj_2Wc","name":null,"slugs":[{"id":9,"slug":"Filosofia"}]},"teacher":{"id":"tcher_r9y","fullName":null,"slugs":[{"id":8,"slug":"Devanir"}]},"weekDayOrder":2,"absoluteDay":1660708800000},{"id":3032,"order":1,"subject":{"id":"subj_wca","name":null,"slugs":[{"id":2,"slug":"Inglês"}]},"teacher":{"id":"tcher_u69","fullName":null,"slugs":[{"id":2,"slug":"Marco V."}]},"weekDayOrder":2,"absoluteDay":1660708800000},{"id":3033,"order":2,"subject":{"id":"subj_iEw","name":null,"slugs":[{"id":12,"slug":"Sociologia"}]},"teacher":{"id":"tcher_5gj","fullName":null,"slugs":[{"id":11,"slug":"Miguel"}]},"weekDayOrder":2,"absoluteDay":1660708800000},{"id":3034,"order":3,"subject":{"id":"subj_5sX","name":null,"slugs":[{"id":13,"slug":"Física"}]},"teacher":{"id":"tcher_hXM","fullName":null,"slugs":[{"id":12,"slug":"Yara"}]},"weekDayOrder":2,"absoluteDay":1660708800000},{"id":3035,"order":4,"subject":{"id":"subj_5sX","name":null,"slugs":[{"id":13,"slug":"Física"}]},"teacher":{"id":"tcher_hXM","fullName":null,"slugs":[{"id":12,"slug":"Yara"}]},"weekDayOrder":2,"absoluteDay":1660708800000},{"id":3036,"order":5,"subject":null,"teacher":null,"weekDayOrder":2,"absoluteDay":1660708800000},{"id":3037,"order":6,"subject":null,"teacher":null,"weekDayOrder":2,"absoluteDay":1660708800000},{"id":3038,"order":7,"subject":null,"teacher":null,"weekDayOrder":2,"absoluteDay":1660708800000},{"id":3039,"order":8,"subject":null,"teacher":null,"weekDayOrder":2,"absoluteDay":1660708800000},{"id":3040,"order":9,"subject":null,"teacher":null,"weekDayOrder":2,"absoluteDay":1660708800000},{"id":3181,"order":0,"subject":{"id":"subj_3uh","name":null,"slugs":[{"id":14,"slug":"História"}]},"teacher":{"id":"tcher_6Jw","fullName":null,"slugs":[{"id":16,"slug":"Mônica"}]},"weekDayOrder":3,"absoluteDay":1660795200000},{"id":3182,"order":1,"subject":{"id":"subj_3uh","name":null,"slugs":[{"id":14,"slug":"História"}]},"teacher":{"id":"tcher_6Jw","fullName":null,"slugs":[{"id":16,"slug":"Mônica"}]},"weekDayOrder":3,"absoluteDay":1660795200000},{"id":3183,"order":2,"subject":{"id":"subj_m86","name":null,"slugs":[{"id":17,"slug":"O.P.P.P"}]},"teacher":{"id":"tcher_ea3","fullName":null,"slugs":[{"id":22,"slug":"Fernando P."}]},"weekDayOrder":3,"absoluteDay":1660795200000},{"id":3184,"order":3,"subject":{"id":"subj_m86","name":null,"slugs":[{"id":17,"slug":"O.P.P.P"}]},"teacher":{"id":"tcher_ea3","fullName":null,"slugs":[{"id":22,"slug":"Fernando P."}]},"weekDayOrder":3,"absoluteDay":1660795200000},{"id":3185,"order":4,"subject":null,"teacher":null,"weekDayOrder":3,"absoluteDay":1660795200000},{"id":3186,"order":5,"subject":{"id":"subj_2Sv","name":null,"slugs":[{"id":3,"slug":"Português"}]},"teacher":{"id":"tcher_k69","fullName":null,"slugs":[{"id":14,"slug":"Luis"}]},"weekDayOrder":3,"absoluteDay":1660795200000},{"id":3187,"order":6,"subject":{"id":"subj_2Sv","name":null,"slugs":[{"id":3,"slug":"Português"}]},"teacher":{"id":"tcher_k69","fullName":null,"slugs":[{"id":14,"slug":"Luis"}]},"weekDayOrder":3,"absoluteDay":1660795200000},{"id":3188,"order":7,"subject":{"id":"subj_2Sv","name":null,"slugs":[{"id":3,"slug":"Português"}]},"teacher":{"id":"tcher_k69","fullName":null,"slugs":[{"id":14,"slug":"Luis"}]},"weekDayOrder":3,"absoluteDay":1660795200000},{"id":3189,"order":8,"subject":{"id":"subj_qSL","name":null,"slugs":[{"id":4,"slug":"Matemática"}]},"teacher":{"id":"tcher_6dJ","fullName":null,"slugs":[{"id":15,"slug":"Mauro"}]},"weekDayOrder":3,"absoluteDay":1660795200000},{"id":3190,"order":9,"subject":null,"teacher":null,"weekDayOrder":3,"absoluteDay":1660795200000},{"id":3331,"order":0,"subject":null,"teacher":null,"weekDayOrder":4,"absoluteDay":1660881600000},{"id":3332,"order":1,"subject":{"id":"subj_dzz","name":null,"slugs":[{"id":6,"slug":"Biologia"}]},"teacher":{"id":"tcher_dpf","fullName":null,"slugs":[{"id":20,"slug":"Maysa"}]},"weekDayOrder":4,"absoluteDay":1660881600000},{"id":3333,"order":2,"subject":{"id":"subj_dzz","name":null,"slugs":[{"id":6,"slug":"Biologia"}]},"teacher":{"id":"tcher_dpf","fullName":null,"slugs":[{"id":20,"slug":"Maysa"}]},"weekDayOrder":4,"absoluteDay":1660881600000},{"id":3334,"order":3,"subject":null,"teacher":null,"weekDayOrder":4,"absoluteDay":1660881600000},{"id":3335,"order":4,"subject":null,"teacher":null,"weekDayOrder":4,"absoluteDay":1660881600000},{"id":3336,"order":5,"subject":null,"teacher":null,"weekDayOrder":4,"absoluteDay":1660881600000},{"id":3337,"order":6,"subject":null,"teacher":null,"weekDayOrder":4,"absoluteDay":1660881600000},{"id":3338,"order":7,"subject":null,"teacher":null,"weekDayOrder":4,"absoluteDay":1660881600000},{"id":3339,"order":8,"subject":null,"teacher":null,"weekDayOrder":4,"absoluteDay":1660881600000},{"id":3340,"order":9,"subject":null,"teacher":null,"weekDayOrder":4,"absoluteDay":1660881600000},{"id":3481,"order":0,"subject":{"id":"subj_3uh","name":null,"slugs":[{"id":14,"slug":"História"}]},"teacher":{"id":"tcher_6Jw","fullName":null,"slugs":[{"id":16,"slug":"Mônica"}]},"weekDayOrder":5,"absoluteDay":1660968000000},{"id":3482,"order":1,"subject":{"id":"subj_3uh","name":null,"slugs":[{"id":14,"slug":"História"}]},"teacher":{"id":"tcher_6Jw","fullName":null,"slugs":[{"id":16,"slug":"Mônica"}]},"weekDayOrder":5,"absoluteDay":1660968000000},{"id":3483,"order":2,"subject":{"id":"subj_m86","name":null,"slugs":[{"id":17,"slug":"O.P.P.P"}]},"teacher":{"id":"tcher_ea3","fullName":null,"slugs":[{"id":22,"slug":"Fernando P."}]},"weekDayOrder":5,"absoluteDay":1660968000000},{"id":3484,"order":3,"subject":{"id":"subj_m86","name":null,"slugs":[{"id":17,"slug":"O.P.P.P"}]},"teacher":{"id":"tcher_ea3","fullName":null,"slugs":[{"id":22,"slug":"Fernando P."}]},"weekDayOrder":5,"absoluteDay":1660968000000},{"id":3485,"order":4,"subject":null,"teacher":null,"weekDayOrder":5,"absoluteDay":1660968000000},{"id":3486,"order":5,"subject":{"id":"subj_2Sv","name":null,"slugs":[{"id":3,"slug":"Português"}]},"teacher":{"id":"tcher_k69","fullName":null,"slugs":[{"id":14,"slug":"Luis"}]},"weekDayOrder":5,"absoluteDay":1660968000000},{"id":3487,"order":6,"subject":{"id":"subj_2Sv","name":null,"slugs":[{"id":3,"slug":"Português"}]},"teacher":{"id":"tcher_k69","fullName":null,"slugs":[{"id":14,"slug":"Luis"}]},"weekDayOrder":5,"absoluteDay":1660968000000},{"id":3488,"order":7,"subject":{"id":"subj_2Sv","name":null,"slugs":[{"id":3,"slug":"Português"}]},"teacher":{"id":"tcher_k69","fullName":null,"slugs":[{"id":14,"slug":"Luis"}]},"weekDayOrder":5,"absoluteDay":1660968000000},{"id":3489,"order":8,"subject":{"id":"subj_qSL","name":null,"slugs":[{"id":4,"slug":"Matemática"}]},"teacher":{"id":"tcher_6dJ","fullName":null,"slugs":[{"id":15,"slug":"Mauro"}]},"weekDayOrder":5,"absoluteDay":1660968000000},{"id":3490,"order":9,"subject":null,"teacher":null,"weekDayOrder":5,"absoluteDay":1660968000000}]}