{"week":{"id":"0001","link":"https://virtual.ifro.edu.br/jiparana/mod/forum/discuss.php?d=19464","title":"HORÁRIO SEMANAL DO TÉCNICO - 25/07 A 30/07/2022","pdfURL":"https://virtual.ifro.edu.br/jiparana/pluginfile.php/50/mod_forum/post/48024/Hor%C3%A1rio%2025%20a%2030%20de%20julho%20%281%29.pdf","publishedAt":"2022-07-22T17:35:40.000Z","startsAt":"2022-07-25T04:00:00.000Z","endsAt":"2022-07-31T03:59:00.000Z"},"teacher":{"id":"tcher_wVv","fullName":null,"slugs":[{"id":40,"slug":"Lourival"}]},"items":[{"id":141,"order":0,"klass":{"id":"florestas-3-A","year":"3","course":"florestas","label":"A","slugs":[{"id":15,"slug":"3ºA FLOR"}]},"subject":{"id":"subj_3uh","name":null,"slugs":[{"id":14,"slug":"História"}]},"weekDayOrder":0,"absoluteDay":1658721600000},{"id":142,"order":1,"klass":{"id":"florestas-3-A","year":"3","course":"florestas","label":"A","slugs":[{"id":15,"slug":"3ºA FLOR"}]},"subject":{"id":"subj_3uh","name":null,"slugs":[{"id":14,"slug":"História"}]},"weekDayOrder":0,"absoluteDay":1658721600000},{"id":99,"order":8,"klass":{"id":"quimica-2-B","year":"2","course":"quimica","label":"B","slugs":[{"id":10,"slug":"2ºB QUI"}]},"subject":{"id":"subj_3uh","name":null,"slugs":[{"id":14,"slug":"História"}]},"weekDayOrder":0,"absoluteDay":1658721600000},{"id":100,"order":9,"klass":{"id":"quimica-2-B","year":"2","course":"quimica","label":"B","slugs":[{"id":10,"slug":"2ºB QUI"}]},"subject":{"id":"subj_3uh","name":null,"slugs":[{"id":14,"slug":"História"}]},"weekDayOrder":0,"absoluteDay":1658721600000},{"id":383,"order":2,"klass":{"id":"quimica-2-A","year":"2","course":"quimica","label":"A","slugs":[{"id":9,"slug":"2ºA QUI"}]},"subject":{"id":"subj_3uh","name":null,"slugs":[{"id":14,"slug":"História"}]},"weekDayOrder":2,"absoluteDay":1658894400000},{"id":384,"order":3,"klass":{"id":"quimica-2-A","year":"2","course":"quimica","label":"A","slugs":[{"id":9,"slug":"2ºA QUI"}]},"subject":{"id":"subj_3uh","name":null,"slugs":[{"id":14,"slug":"História"}]},"weekDayOrder":2,"absoluteDay":1658894400000},{"id":557,"order":6,"klass":{"id":"quimica-3-A","year":"3","course":"quimica","label":"A","slugs":[{"id":11,"slug":"3ºA QUI"}]},"subject":{"id":"subj_3uh","name":null,"slugs":[{"id":14,"slug":"História"}]},"weekDayOrder":3,"absoluteDay":1658980800000},{"id":558,"order":7,"klass":{"id":"quimica-3-A","year":"3","course":"quimica","label":"A","slugs":[{"id":11,"slug":"3ºA QUI"}]},"subject":{"id":"subj_3uh","name":null,"slugs":[{"id":14,"slug":"História"}]},"weekDayOrder":3,"absoluteDay":1658980800000},{"id":569,"order":8,"klass":{"id":"quimica-3-B","year":"3","course":"quimica","label":"B","slugs":[{"id":12,"slug":"3ºB QUI"}]},"subject":{"id":"subj_3uh","name":null,"slugs":[{"id":14,"slug":"História"}]},"weekDayOrder":3,"absoluteDay":1658980800000},{"id":570,"order":9,"klass":{"id":"quimica-3-B","year":"3","course":"quimica","label":"B","slugs":[{"id":12,"slug":"3ºB QUI"}]},"subject":{"id":"subj_3uh","name":null,"slugs":[{"id":14,"slug":"História"}]},"weekDayOrder":3,"absoluteDay":1658980800000},{"id":891,"order":0,"klass":{"id":"florestas-3-A","year":"3","course":"florestas","label":"A","slugs":[{"id":15,"slug":"3ºA FLOR"}]},"subject":{"id":"subj_3uh","name":null,"slugs":[{"id":14,"slug":"História"}]},"weekDayOrder":5,"absoluteDay":1659153600000},{"id":892,"order":1,"klass":{"id":"florestas-3-A","year":"3","course":"florestas","label":"A","slugs":[{"id":15,"slug":"3ºA FLOR"}]},"subject":{"id":"subj_3uh","name":null,"slugs":[{"id":14,"slug":"História"}]},"weekDayOrder":5,"absoluteDay":1659153600000},{"id":849,"order":8,"klass":{"id":"quimica-2-B","year":"2","course":"quimica","label":"B","slugs":[{"id":10,"slug":"2ºB QUI"}]},"subject":{"id":"subj_3uh","name":null,"slugs":[{"id":14,"slug":"História"}]},"weekDayOrder":5,"absoluteDay":1659153600000},{"id":850,"order":9,"klass":{"id":"quimica-2-B","year":"2","course":"quimica","label":"B","slugs":[{"id":10,"slug":"2ºB QUI"}]},"subject":{"id":"subj_3uh","name":null,"slugs":[{"id":14,"slug":"História"}]},"weekDayOrder":5,"absoluteDay":1659153600000}]}