{"week":{"id":"000c","link":"https://virtual.ifro.edu.br/jiparana/mod/forum/discuss.php?d=19687","title":"HORÁRIO SEMANAL DO TÉCNICO - 10 A 14/10/2022","pdfURL":"https://virtual.ifro.edu.br/jiparana/pluginfile.php/50/mod_forum/post/48482/Hor%C3%A1rio%2010%20a%2014%20de%20outubro%20%281%29.pdf","publishedAt":"2022-10-10T00:55:58.000Z","startsAt":"2022-10-10T04:00:00.000Z","endsAt":"2022-10-15T03:59:00.000Z"},"teacher":{"id":"tcher_v2N","fullName":null,"slugs":[{"id":60,"slug":"Eiva"}]},"items":[{"id":10022,"order":1,"klass":{"id":"florestas-1-A","year":"1","course":"florestas","label":"A","slugs":[{"id":13,"slug":"1ºA FLOR"}]},"subject":{"id":"subj_bGe","name":null,"slugs":[{"id":27,"slug":"Química"}]},"weekDayOrder":0,"absoluteDay":1665374400000},{"id":10023,"order":2,"klass":{"id":"florestas-1-A","year":"1","course":"florestas","label":"A","slugs":[{"id":13,"slug":"1ºA FLOR"}]},"subject":{"id":"subj_bGe","name":null,"slugs":[{"id":27,"slug":"Química"}]},"weekDayOrder":0,"absoluteDay":1665374400000}]}